{"last_bias": "Short", "last_digest_date": "2026-07-16", "open_trade": {"bias": "Short", "reason": "Short-term trend is down and RSI confirms momentum without being oversold.", "strategy": "trend", "entry_low": 3980.14, "entry_high": 3981.38, "stop_loss": 3986.95, "tp1": 3976.64, "tp2": 3971.49, "tp3": 3966.34, "opened_at": "2026-07-16T17:45:25.621217", "tp1_hit": false, "tp2_hit": false, "realized_r": 0.0}, "last_setup": {"bias": "Short", "reason": "Short-term trend is down and RSI confirms momentum without being oversold.", "strategy": "trend", "entry_low": 3980.14, "entry_high": 3981.38, "stop_loss": 3986.95, "tp1": 3976.64, "tp2": 3971.49, "tp3": 3966.34}}